sk/__init__.py
sk/mod1.py
sk/mod2.py
sk/package/__init__.py
sk/package/__main__.py
sk/package/mod1.py
sk/package/sk.py
sk/package/upload.py
sk/package/lib/__init__.py
sk/package/lib/lib.py
skoy-0.0.1.dist-info/LICENSE
skoy-0.0.1.dist-info/METADATA
skoy-0.0.1.dist-info/WHEEL
skoy-0.0.1.dist-info/entry_points.txt
skoy-0.0.1.dist-info/top_level.txt
skoy-0.0.1.dist-info/RECORD
