Metadata-Version: 2.1
Name: skoy
Version: 0.0.1
Summary: A small example package
Home-page: https://github.com/pypa/sampleproject
Author: Bruno Gomes
Author-email: bgomes@youongroup.com
License: Apache License 2.0
Platform: UNKNOWN
Classifier: Programming Language :: Python :: 3
Classifier: License :: OSI Approved :: MIT License
Classifier: Operating System :: OS Independent
Requires-Python: >=3.6
Requires-Dist: requests
Requires-Dist: beautifulsoup4
Requires-Dist: tqdm
Requires-Dist: lxml
